enocean4ha_bridge/__init__.py
enocean4ha_bridge/binary_sensor.py
enocean4ha_bridge/common.py
enocean4ha_bridge/constants.py
enocean4ha_bridge/gateway.py
enocean4ha_bridge/light.py
enocean4ha_bridge/sensor.py
enocean4ha_bridge/switch.py
enocean4ha_bridge-0.1.0.dist-info/LICENSE
enocean4ha_bridge-0.1.0.dist-info/METADATA
enocean4ha_bridge-0.1.0.dist-info/WHEEL
enocean4ha_bridge-0.1.0.dist-info/top_level.txt
enocean4ha_bridge-0.1.0.dist-info/RECORD
